{
  "categories": [
    { "id": "cc-tier-1", "label": "CC — Platform Foundation", "icon": "🧱", "color": "#3b82f6" },
    { "id": "cc-tier-2", "label": "CC — Platform Features", "icon": "⚙️", "color": "#6366f1" },
    { "id": "cc-tier-3", "label": "CC — Commerce Core", "icon": "🛒", "color": "#8b5cf6" },
    { "id": "cc-tier-4", "label": "CC — Backoffice & CMS", "icon": "🖥️", "color": "#a855f7" },
    { "id": "cc-tier-5", "label": "CC — APIs & Integration", "icon": "🔗", "color": "#7c3aed" },
    { "id": "cc-tier-6", "label": "CC — CCV2 & Cloud", "icon": "☁️", "color": "#2563eb" },
    { "id": "cc-tier-7", "label": "CC — Composable Storefront", "icon": "🏪", "color": "#1d4ed8" },
    { "id": "cpq-phase-1", "label": "CPQ — Foundation", "icon": "⚙️", "color": "#f59e0b" },
    { "id": "cpq-phase-2", "label": "CPQ — Configuration", "icon": "🔧", "color": "#f97316" },
    { "id": "cpq-phase-3", "label": "CPQ — Pricing & Quoting", "icon": "💰", "color": "#ef4444" },
    { "id": "cpq-phase-4", "label": "CPQ — Integration & Architecture", "icon": "🔗", "color": "#8b5cf6" }
  ],
  "topics": [
    "cc-typesystem",
    "cc-spring-basics",
    "cc-servicelayer",
    "cc-flexiblesearch",
    "cc-interceptors",
    "cc-extensions",
    "cc-impex",
    "cc-cronjobs",
    "cc-caching",
    "cc-search-solr",
    "cc-events",
    "cc-pricing",
    "cc-catalog",
    "cc-cart-checkout",
    "cc-order-management",
    "cc-promotions",
    "cc-vouchers",


    "cpq-overview",
    "cpq-platform-basics",
    "cpq-configurable-products",
    "cpq-rules-engine",
    "cpq-scripting",
    "cpq-guided-selling",
    "cpq-advanced-config",
    "cpq-pricing",
    "cpq-quote-management",
    "cpq-approvals",
    "cpq-document-generation",
    "cpq-sap-integrations",
    "cpq-apis",
    "cpq-external-integrations",
    "cpq-architecture"
  ]
}